jsz-2025.6.6.dist-info/METADATA
jsz-2025.6.6.dist-info/WHEEL
jsz-2025.6.6.dist-info/entry_points.txt
jsz/__init__.py
jsz/_db.py
jsz/_html.py
jsz/_http.py
jsz/_richx.py
jsz/_tools.py
jsz-2025.6.6.dist-info/RECORD
