Metadata-Version: 2.1
Name: jsz
Version: 2025.6.6
Summary: 金手指
Author: jiaosenvip
Author-Email: jiaosenvip <jiaosenvip@163.com>
License: MIT
Project-URL: HomePage, https://github.com/jiaosenvip/jsz
Project-URL: Documentation, https://github.com/jiaosenvip/jsz/wiki
Requires-Python: >=3.11
Requires-Dist: beautifulsoup4>=4.13.0
Requires-Dist: diskcache>=5.6.3
Requires-Dist: demjson3>=3.0.0
Requires-Dist: faker>=37.1.0
Requires-Dist: html2text>=2025.4.15
Requires-Dist: httpx[http2]>=0.28.0
Requires-Dist: ipython>=9.2.0
Requires-Dist: js2py>=0.74
Requires-Dist: jsonpath>=0.82.0
Requires-Dist: loguru>=0.7.3
Requires-Dist: markdown>=3.8.0
Requires-Dist: pymysql>=1.1.1
Requires-Dist: newpool>=0.1.0
Requires-Dist: oss2>=2.19.1
Requires-Dist: parsel>=1.10.0
Requires-Dist: pandas[excel]>=2.2.3
Requires-Dist: pycryptodome>=3.22.0
Requires-Dist: pymongo>=4.12.1
Requires-Dist: pypdf>=5.5.0
Requires-Dist: python-dateutil>=2.9.0
Requires-Dist: rich>=14.0.0
Requires-Dist: redis>=6.2.0
Requires-Dist: requests>=2.32.3
Requires-Dist: plyer>=2.1.0
Provides-Extra: all
Requires-Dist: curl_cffi>=0.10.0; extra == "all"
Requires-Dist: fabric>=3.2.2; extra == "all"
Requires-Dist: dateparser>=1.2.1; extra == "all"
Requires-Dist: ddddocr>=1.5.6; extra == "all"
Requires-Dist: duckdb>=1.3.0; extra == "all"
Requires-Dist: moviepy>=2.1.2; extra == "all"
Requires-Dist: pyperclip>=1.9.0; extra == "all"
Requires-Dist: polars>=1.29.0; extra == "all"
